test_material_brain/__init__.py
test_material_brain/library.py
test_material_brain/scratch/__init__.py
test_material_brain/scratch/panorama.py
test_material_brain/scratch/scratch.py
test_material_brain-0.0.3.dist-info/METADATA
test_material_brain-0.0.3.dist-info/WHEEL
test_material_brain-0.0.3.dist-info/top_level.txt
test_material_brain-0.0.3.dist-info/RECORD
