Metadata-Version: 2.1
Name: test-material-brain
Version: 0.0.3
Summary: A simple python package for testing
Author: Stephane Chattot
Author-email: stephane.chattot@heig-vd.ch
License: UNKNOWN
Keywords: python,test,package,material_brain
Platform: UNKNOWN
Classifier: Development Status :: 3 - Alpha
Requires-Dist: numpy
Requires-Dist: scipy
Requires-Dist: scikit-image
Requires-Dist: matplotlib
Requires-Dist: pandas
Requires-Dist: sklearn
Requires-Dist: ssqueezepy
Requires-Dist: openpyxl
